odoo9_addon_medical-9.0.1.0.0-py2.7-nspkg.pth
odoo9_addon_medical-9.0.1.0.0.dist-info/top_level.txt
odoo9_addon_medical-9.0.1.0.0.dist-info/WHEEL
odoo9_addon_medical-9.0.1.0.0.dist-info/RECORD
odoo9_addon_medical-9.0.1.0.0.dist-info/metadata.json
odoo9_addon_medical-9.0.1.0.0.dist-info/DESCRIPTION.rst
odoo9_addon_medical-9.0.1.0.0.dist-info/METADATA
odoo9_addon_medical-9.0.1.0.0.dist-info/namespace_packages.txt
odoo_addons/medical/__openerp__.py
odoo_addons/medical/__init__.py
odoo_addons/medical/medical_constants.py
odoo_addons/medical/README.rst
odoo_addons/medical/security/medical_security.xml
odoo_addons/medical/security/ir.model.access.csv
odoo_addons/medical/models/medical_patient.py
odoo_addons/medical/models/res_partner.py
odoo_addons/medical/models/__init__.py
odoo_addons/medical/views/res_partner_view.xml
odoo_addons/medical/views/medical_patient_view.xml
odoo_addons/medical/views/medical_menu.xml
odoo_addons/medical/data/ir_sequence_data.xml
odoo_addons/medical/tests/__init__.py
odoo_addons/medical/tests/test_medical_patient.py
odoo_addons/medical/demo/medical_patient_demo.xml
odoo_addons/medical/static/description/icon.png
